<?xml version="1.0" encoding="UTF-8" ?>
<!DOCTYPE mapper PUBLIC "-//mybatis.org//DTD Mapper 3.0//EN" "http://mybatis.org/dtd/mybatis-3-mapper.dtd" >
<mapper namespace="net.okdi.api.dao.RobPushRelationMapper" >
  <resultMap id="BaseResultMap" type="net.okdi.api.entity.RobPushRelation" >
    <!--
      WARNING - @mbggenerated
      This element is automatically generated by MyBatis Generator, do not modify.
      This element was generated on Wed Jun 17 13:05:37 CST 2015.
    -->
    <id column="relation_id" property="relationId" jdbcType="BIGINT" />
    <result column="broadcast_id" property="broadcastId" jdbcType="BIGINT" />
    <result column="comp_id" property="compId" jdbcType="BIGINT" />
    <result column="member_id" property="memberId" jdbcType="BIGINT" />
    <result column="create_time" property="createTime" jdbcType="TIMESTAMP" />
  </resultMap>
  <sql id="Base_Column_List" >
    <!--
      WARNING - @mbggenerated
      This element is automatically generated by MyBatis Generator, do not modify.
      This element was generated on Wed Jun 17 13:05:37 CST 2015.
    -->
    relation_id, broadcast_id, comp_id, member_id, create_time
  </sql>
  <select id="selectByPrimaryKey" resultMap="BaseResultMap" parameterType="java.lang.Long" >
    <!--
      WARNING - @mbggenerated
      This element is automatically generated by MyBatis Generator, do not modify.
      This element was generated on Wed Jun 17 13:05:37 CST 2015.
    -->
    select 
    <include refid="Base_Column_List" />
    from rob_push_relation
    where relation_id = #{relationId,jdbcType=BIGINT}
  </select>
  <delete id="deleteByPrimaryKey" parameterType="java.lang.Long" >
    <!--
      WARNING - @mbggenerated
      This element is automatically generated by MyBatis Generator, do not modify.
      This element was generated on Wed Jun 17 13:05:37 CST 2015.
    -->
    delete from rob_push_relation
    where relation_id = #{relationId,jdbcType=BIGINT}
  </delete>
  <insert id="insert" parameterType="net.okdi.api.entity.RobPushRelation" >
    <!--
      WARNING - @mbggenerated
      This element is automatically generated by MyBatis Generator, do not modify.
      This element was generated on Wed Jun 17 13:05:37 CST 2015.
    -->
    insert into rob_push_relation (relation_id, broadcast_id, comp_id, 
      member_id, create_time)
    values (#{relationId,jdbcType=BIGINT}, #{broadcastId,jdbcType=BIGINT}, #{compId,jdbcType=BIGINT}, 
      #{memberId,jdbcType=BIGINT}, #{createTime,jdbcType=TIMESTAMP})
  </insert>
  <insert id="insertSelective" parameterType="net.okdi.api.entity.RobPushRelation" >
    <!--
      WARNING - @mbggenerated
      This element is automatically generated by MyBatis Generator, do not modify.
      This element was generated on Wed Jun 17 13:05:37 CST 2015.
    -->
    insert into rob_push_relation
    <trim prefix="(" suffix=")" suffixOverrides="," >
      <if test="relationId != null" >
        relation_id,
      </if>
      <if test="broadcastId != null" >
        broadcast_id,
      </if>
      <if test="compId != null" >
        comp_id,
      </if>
      <if test="memberId != null" >
        member_id,
      </if>
      <if test="createTime != null" >
        create_time,
      </if>
    </trim>
    <trim prefix="values (" suffix=")" suffixOverrides="," >
      <if test="relationId != null" >
        #{relationId,jdbcType=BIGINT},
      </if>
      <if test="broadcastId != null" >
        #{broadcastId,jdbcType=BIGINT},
      </if>
      <if test="compId != null" >
        #{compId,jdbcType=BIGINT},
      </if>
      <if test="memberId != null" >
        #{memberId,jdbcType=BIGINT},
      </if>
      <if test="createTime != null" >
        #{createTime,jdbcType=TIMESTAMP},
      </if>
    </trim>
  </insert>
  <update id="updateByPrimaryKeySelective" parameterType="net.okdi.api.entity.RobPushRelation" >
    <!--
      WARNING - @mbggenerated
      This element is automatically generated by MyBatis Generator, do not modify.
      This element was generated on Wed Jun 17 13:05:37 CST 2015.
    -->
    update rob_push_relation
    <set >
      <if test="broadcastId != null" >
        broadcast_id = #{broadcastId,jdbcType=BIGINT},
      </if>
      <if test="compId != null" >
        comp_id = #{compId,jdbcType=BIGINT},
      </if>
      <if test="memberId != null" >
        member_id = #{memberId,jdbcType=BIGINT},
      </if>
      <if test="createTime != null" >
        create_time = #{createTime,jdbcType=TIMESTAMP},
      </if>
    </set>
    where relation_id = #{relationId,jdbcType=BIGINT}
  </update>
  <update id="updateByPrimaryKey" parameterType="net.okdi.api.entity.RobPushRelation" >
    <!--
      WARNING - @mbggenerated
      This element is automatically generated by MyBatis Generator, do not modify.
      This element was generated on Wed Jun 17 13:05:38 CST 2015.
    -->
    update rob_push_relation
    set broadcast_id = #{broadcastId,jdbcType=BIGINT},
      comp_id = #{compId,jdbcType=BIGINT},
      member_id = #{memberId,jdbcType=BIGINT},
      create_time = #{createTime,jdbcType=TIMESTAMP}
    where relation_id = #{relationId,jdbcType=BIGINT}
  </update>
  <insert id="batchRobPushRelation" parameterType="net.okdi.api.entity.RobPushRelation" >
    insert into rob_push_relation (relation_id, broadcast_id, comp_id, 
      member_id, create_time)
    values 
    <foreach collection="list" item="item" index="index" separator="," >
    (#{item.relationId,jdbcType=BIGINT}, #{item.broadcastId,jdbcType=BIGINT}, #{item.compId,jdbcType=BIGINT}, 
      #{item.memberId,jdbcType=BIGINT}, #{item.createTime,jdbcType=TIMESTAMP})
    </foreach>
  </insert>
  <select id="selectMemberIdsByBroadcastId" resultType="java.lang.Long" parameterType="java.lang.Long" >
    select 
    member_id 
    from rob_push_relation
    where broadcast_id = #{broadcastId,jdbcType=BIGINT}
  </select>
</mapper>